wsipipe/__init__.py
wsipipe/cli.py
wsipipe/datasets/__init__.py
wsipipe/datasets/camelyon16.py
wsipipe/datasets/dataset_utils.py
wsipipe/datasets/stripai.py
wsipipe/load/__init__.py
wsipipe/load/annotations/__init__.py
wsipipe/load/annotations/annotation.py
wsipipe/load/annotations/asapxml.py
wsipipe/load/annotations/geojson.py
wsipipe/load/datasets/__init__.py
wsipipe/load/datasets/camelyon16.py
wsipipe/load/datasets/loader.py
wsipipe/load/datasets/registry.py
wsipipe/load/datasets/stripai.py
wsipipe/load/slides/__init__.py
wsipipe/load/slides/openslide.py
wsipipe/load/slides/region.py
wsipipe/load/slides/slide.py
wsipipe/preprocess/__init__.py
wsipipe/preprocess/patching/__init__.py
wsipipe/preprocess/patching/patch_finder.py
wsipipe/preprocess/patching/patchset.py
wsipipe/preprocess/patching/patchset_utils.py
wsipipe/preprocess/sample/__init__.py
wsipipe/preprocess/sample/sampler.py
wsipipe/preprocess/tissue_detection/__init__.py
wsipipe/preprocess/tissue_detection/filters.py
wsipipe/preprocess/tissue_detection/morphology_transforms.py
wsipipe/preprocess/tissue_detection/tissue_detector.py
wsipipe/preprocess/tissue_detection/visualise.py
wsipipe/utils/__init__.py
wsipipe/utils/convert.py
wsipipe/utils/filters.py
wsipipe/utils/geometry.py
wsipipe-0.1.6.dist-info/AUTHORS.rst
wsipipe-0.1.6.dist-info/LICENSE
wsipipe-0.1.6.dist-info/METADATA
wsipipe-0.1.6.dist-info/WHEEL
wsipipe-0.1.6.dist-info/entry_points.txt
wsipipe-0.1.6.dist-info/top_level.txt
wsipipe-0.1.6.dist-info/RECORD
