Metadata-Version: 2.1
Name: wsipipe
Version: 0.1.6
Summary: A set of tools for processing pathology whole slide images for deep learning.
Home-page: https://github.com/davemor/wsipipe
Author: David Morrison, Christina Fell
Author-email: dm236@st-andrews.ac.uk, cmf21@st-andrews.ac.uk
License: MIT license
Keywords: wsipipe
Platform: UNKNOWN
Classifier: Development Status :: 2 - Pre-Alpha
Classifier: Intended Audience :: Developers
Classifier: License :: OSI Approved :: MIT License
Classifier: Natural Language :: English
Classifier: Programming Language :: Python :: 3
Classifier: Programming Language :: Python :: 3.5
Classifier: Programming Language :: Python :: 3.6
Classifier: Programming Language :: Python :: 3.7
Classifier: Programming Language :: Python :: 3.8
Requires-Python: >=3.5
License-File: LICENSE
License-File: AUTHORS.rst
Requires-Dist: scipy
Requires-Dist: scikit-image
Requires-Dist: pandas
Requires-Dist: numpy
Requires-Dist: opencv-python-headless (==4.5.5.64)
Requires-Dist: Pillow
Requires-Dist: openslide-python
